{"id": "problem22", "title": "冒泡排序", "difficulty": "medium", "description": "输入 n 个整数，用冒泡排序将它们从小到大排序输出", "testCases": [{"input": "5\n3 1 4 2 5", "output": "1 2 3 4 5"}, {"input": "3\n3 2 1", "output": "1 2 3"}, {"input": "4\n1 1 1 1", "output": "1 1 1 1"}], "referenceSolution": "#include <iostream>\n\nint main() {\n    int n;\n    std::cin >> n;\n    int arr[1000];\n    for (int i = 0; i < n; i++) {\n        std::cin >> arr[i];\n    }\n    for (int i = 0; i < n - 1; i++) {\n        for (int j = 0; j < n - 1 - i; j++) {\n            if (arr[j] > arr[j + 1]) {\n                int temp = arr[j];\n                arr[j] = arr[j + 1];\n                arr[j + 1] = temp;\n            }\n        }\n    }\n    for (int i = 0; i < n; i++) {\n        std::cout << arr[i];\n        if (i < n - 1) std::cout << \" \";\n    }\n    std::cout << std::endl;\n    return 0;\n}"}